Metadata-Version: 2.1
Name: ticgithub
Version: 0.2.1
Summary: Use GitHub as a ticketing system for shared GMail
Home-page: https://github.com/dwhswenson/ticgithub
Author: David W.H. Swenson
Author-email: dwhs@hyperblazer.net
License: MIT
Classifier: Development Status :: 2 - Pre-Alpha
Classifier: Environment :: Console
Classifier: Environment :: MacOS X
Classifier: Environment :: Win32 (MS Windows)
Classifier: Intended Audience :: Customer Service
Classifier: Intended Audience :: Developers
Classifier: Intended Audience :: Information Technology
Classifier: License :: OSI Approved :: MIT License
Classifier: Natural Language :: English
Classifier: Operating System :: MacOS :: MacOS X
Classifier: Operating System :: Microsoft :: Windows
Classifier: Operating System :: POSIX
Classifier: Programming Language :: Python :: 3.8
Classifier: Programming Language :: Python :: 3.9
Classifier: Programming Language :: Python :: 3.10
Classifier: Topic :: Communications :: Email
Classifier: Topic :: Office/Business :: Groupware
Classifier: Topic :: Software Development :: Bug Tracking
Requires-Python: >=3.8
License-File: LICENSE
Requires-Dist: pyyaml
Requires-Dist: pygithub
